universalcolor/__init__.py
universalcolor/color.py
universalcolor/colordata/colordata.py
universalcolor/colordata/colornames.py
universalcolor-24.7.1.dist-info/LICENSE-lgpl-3.0.md
universalcolor-24.7.1.dist-info/METADATA
universalcolor-24.7.1.dist-info/WHEEL
universalcolor-24.7.1.dist-info/RECORD
